winzy_taskloop/__init__.py
winzy_taskloop-0.1.0.dist-info/LICENSE
winzy_taskloop-0.1.0.dist-info/METADATA
winzy_taskloop-0.1.0.dist-info/WHEEL
winzy_taskloop-0.1.0.dist-info/entry_points.txt
winzy_taskloop-0.1.0.dist-info/top_level.txt
winzy_taskloop-0.1.0.dist-info/RECORD
