Metadata-Version: 2.2
Name: winzy-taskloop
Version: 0.1.0
Summary: Run tasks in loop from cli
Author: sukhbinder singh
License: Apache-2.0
Project-URL: Homepage, https://github.com/sukhbinder/winzy-taskloop
Project-URL: Changelog, https://github.com/sukhbinder/winzy-taskloop/releases
Project-URL: Issues, https://github.com/sukhbinder/winzy-taskloop/issues
Project-URL: CI, https://github.com/sukhbinder/winzy-taskloop/actions
Classifier: License :: OSI Approved :: Apache Software License
License-File: LICENSE
Requires-Dist: winzy
Provides-Extra: test
Requires-Dist: pytest; extra == "test"
